dodeka/__init__.py
dodeka/factors.py
dodeka/interface.py
dodeka/test_factors.py
dodeka/test_interface.py
dodeka-0.3.0.dist-info/LICENSE
dodeka-0.3.0.dist-info/METADATA
dodeka-0.3.0.dist-info/WHEEL
dodeka-0.3.0.dist-info/entry_points.txt
dodeka-0.3.0.dist-info/top_level.txt
dodeka-0.3.0.dist-info/RECORD
