Metadata-Version: 2.1
Name: dodeka
Version: 0.3.0
Summary: Twelve-Factor App Checker
Home-page: https://github.com/shimst3r/dodeka
Author: Nils P. Müller
Author-email: shimst3r@gmail.com
License: MIT
Download-URL: https://github.com/shimst3r/dodeka/archive/0.3.0.tar.gz
Keywords: cli,tool,twelvefactor
Platform: UNKNOWN
Classifier: Development Status :: 3 - Alpha
Classifier: Intended Audience :: Developers
Classifier: License :: OSI Approved :: MIT License
Classifier: Programming Language :: Python :: 3
Classifier: Programming Language :: Python :: 3.7
Requires-Python: >=3.7
Requires-Dist: Click
Requires-Dist: jinja2
